{
  "main": {
    "id": "8fc74f97268f6a97",
    "type": "split",
    "children": [
      {
        "id": "31e55ea6fe509418",
        "type": "tabs",
        "children": [
          {
            "id": "534bcd52e88d2cbe",
            "type": "leaf",
            "state": {
              "type": "database-plugin",
              "state": {
                "file": "Database/orgs-db.md"
              }
            }
          }
        ]
      }
    ],
    "direction": "vertical"
  },
  "left": {
    "id": "960e12fd0bca948e",
    "type": "split",
    "children": [
      {
        "id": "093c8b123f183529",
        "type": "tabs",
        "children": [
          {
            "id": "33a657314c41c01c",
            "type": "leaf",
            "state": {
              "type": "file-explorer",
              "state": {
                "sortOrder": "alphabetical"
              }
            }
          },
          {
            "id": "e9127ecf6fcbe455",
            "type": "leaf",
            "state": {
              "type": "search",
              "state": {
                "query": "",
                "matchingCase": false,
                "explainSearch": false,
                "collapseAll": false,
                "extraContext": false,
                "sortOrder": "alphabetical"
              }
            }
          },
          {
            "id": "ec03aafd9c9e630d",
            "type": "leaf",
            "state": {
              "type": "bookmarks",
              "state": {}
            }
          }
        ]
      }
    ],
    "direction": "horizontal",
    "width": 300
  },
  "right": {
    "id": "b5202fc157ea6ba3",
    "type": "split",
    "children": [
      {
        "id": "9351ae2db552e0a6",
        "type": "tabs",
        "children": [
          {
            "id": "8c041ded9967b2a3",
            "type": "leaf",
            "state": {
              "type": "backlink",
              "state": {
                "file": "Database/orgs-db.md",
                "collapseAll": false,
                "extraContext": false,
                "sortOrder": "alphabetical",
                "showSearch": false,
                "searchQuery": "",
                "backlinkCollapsed": false,
                "unlinkedCollapsed": true
              }
            }
          },
          {
            "id": "5669301f63d4ae2b",
            "type": "leaf",
            "state": {
              "type": "outgoing-link",
              "state": {
                "file": "Database/orgs-db.md",
                "linksCollapsed": false,
                "unlinkedCollapsed": true
              }
            }
          },
          {
            "id": "263c58305251f53f",
            "type": "leaf",
            "state": {
              "type": "tag",
              "state": {
                "sortOrder": "frequency",
                "useHierarchy": true
              }
            }
          },
          {
            "id": "3104901ad9ed0d99",
            "type": "leaf",
            "state": {
              "type": "outline",
              "state": {
                "file": "Database/orgs-db.md"
              }
            }
          }
        ]
      }
    ],
    "direction": "horizontal",
    "width": 300,
    "collapsed": true
  },
  "left-ribbon": {
    "hiddenItems": {
      "switcher:Open quick switcher": false,
      "canvas:Create new canvas": false,
      "daily-notes:Open today's daily note": false,
      "graph:Open graph view": false,
      "templates:Insert template": false,
      "command-palette:Open command palette": false,
      "templater-obsidian:Templater": false,
      "dbfolder:Create a new database table": false,
      "workspaces:Manage workspace layouts": false
    }
  },
  "active": "534bcd52e88d2cbe",
  "lastOpenFiles": [
    "4. NPCs & Organizations/Organizations/Ashfang Steelworks.md",
    "Database/orgs-db.md",
    "4. NPCs & Organizations/Organizations/Ashfangs.md",
    "1. Player Characters/Shannon.md",
    "Database/char-db.md",
    "4. NPCs & Organizations/NPCs/Bruce.md",
    "Database/location-db.md",
    "4. NPCs & Organizations/NPCs/Vancent.md",
    "4. NPCs & Organizations/NPCs/Jaren.md",
    "Untitled.md",
    "5. Monsters, Items and Terms/Items-Mundane/Dreamlily.md",
    "4. NPCs & Organizations/Organizations/The Shady Bunch.md",
    "3. Locations/Other/Underdark.md",
    "README (DON'T DELETE).md",
    "4. NPCs & Organizations/NPCs/Tahba.md",
    "4. NPCs & Organizations/NPCs/Amnesiac Haundavar.md",
    "1. Player Characters/Leia.md",
    "1. Player Characters/Toble.md",
    "1. Player Characters/Vorn.md",
    "1. Player Characters/Taishi.md",
    "1. Player Characters/Runliel.md",
    "1. Player Characters/Patchclaw.md",
    "1. Player Characters/Ophelia.md",
    "1. Player Characters/Nightingale.md",
    "1. Player Characters/Maahes.md",
    "1. Player Characters/Gyoop.md",
    "z_Attachments/Vorn.png",
    "z_Attachments/YdanynCave.jpg",
    "z_Attachments/YdanynCave_Entrance.jpg",
    "3. Locations/Klisas/South Klisas",
    "3. Locations/Klisas/North Klisas",
    "3. Locations/Aeslea/South",
    "3. Locations/Aeslea/North",
    "3. Locations/Aeslea/West",
    "3. Locations/Other",
    "4. NPCs & Organizations/Organizations/Company",
    "Templates/Commands",
    "Database",
    "5. Monsters, Items and Terms/Items-Magical",
    "z_Attachments/Battlesmith Shannon color.png",
    "z_Attachments/Faal'Krel_Inn.jpg",
    "Untitled.canvas",
    "z_Attachments/purpleworm.png",
    "z_Attachments/Shannon dress.png",
    "z_Attachments/Leia.jpg",
    "z_Attachments/Leia's dream.png",
    "z_Attachments/EyySzJ3U4AEhU8n 1.png"
  ]
}